{
    "LinearRegression": {
        "training_time": 0.004951779999828432,
        "prediction_time": 0.0011178799999470358,
        "evaluation_time": 0.0010764799997559748,
        "mae": 31.46414032311652,
        "mape": 0.16113575105120953,
        "per_fold": [
            {
                "training_time": 0.005031000000599306,
                "prediction_time": 0.0016011999978218228,
                "evaluation_time": 0.0013722000003326684,
                "mae": 31.32642094435688,
                "mape": 0.162449833790528
            },
            {
                "training_time": 0.005162299999938114,
                "prediction_time": 0.00109119999979157,
                "evaluation_time": 0.0009470000004512258,
                "mae": 32.15063711938491,
                "mape": 0.16181913227822614
            },
            {
                "training_time": 0.005013099998905091,
                "prediction_time": 0.001073200000973884,
                "evaluation_time": 0.0008388999995077029,
                "mae": 31.340766048067785,
                "mape": 0.15938395255921914
            },
            {
                "training_time": 0.0048643999980413355,
                "prediction_time": 0.0008641999993415084,
                "evaluation_time": 0.0010708999980124645,
                "mae": 30.813801449882856,
                "mape": 0.16007413787615746
            },
            {
                "training_time": 0.004688100001658313,
                "prediction_time": 0.0009596000018063933,
                "evaluation_time": 0.0011534000004758127,
                "mae": 31.689076053890147,
                "mape": 0.161951698751917
            }
        ]
    },
    "XGBRegressor": {
        "training_time": 0.5805340200007777,
        "prediction_time": 0.005341960000077961,
        "evaluation_time": 0.0008787800004938617,
        "mae": 27.912746810913085,
        "mape": 0.13593468070030212,
        "per_fold": [
            {
                "training_time": 0.6546893999984604,
                "prediction_time": 0.005491299998539034,
                "evaluation_time": 0.000932999999349704,
                "mae": 27.8016300201416,
                "mape": 0.13709352910518646
            },
            {
                "training_time": 0.5418215000026976,
                "prediction_time": 0.00441069999942556,
                "evaluation_time": 0.0009026000006997492,
                "mae": 28.469524383544922,
                "mape": 0.13700135052204132
            },
            {
                "training_time": 0.5563761000012164,
                "prediction_time": 0.005400900001404807,
                "evaluation_time": 0.0008866999996826053,
                "mae": 28.011606216430664,
                "mape": 0.1350836604833603
            },
            {
                "training_time": 0.5610845000010158,
                "prediction_time": 0.005534100000659237,
                "evaluation_time": 0.00079340000229422,
                "mae": 27.19738006591797,
                "mape": 0.13427650928497314
            },
            {
                "training_time": 0.5886986000004981,
                "prediction_time": 0.005872800000361167,
                "evaluation_time": 0.0008782000004430301,
                "mae": 28.083593368530273,
                "mape": 0.1362183541059494
            }
        ]
    },
    "LGBMRegressor": {
        "training_time": 0.4234678200002236,
        "prediction_time": 0.006523180001386209,
        "evaluation_time": 0.0011293800002022182,
        "mae": 27.804383054062974,
        "mape": 0.13403129095076513,
        "per_fold": [
            {
                "training_time": 1.5870547000013175,
                "prediction_time": 0.006508999998914078,
                "evaluation_time": 0.0011546999994607177,
                "mae": 27.66835395244136,
                "mape": 0.1346962360776964
            },
            {
                "training_time": 0.14030369999818504,
                "prediction_time": 0.00695340000311262,
                "evaluation_time": 0.0011965000012423843,
                "mae": 28.311339928137595,
                "mape": 0.13479425353297414
            },
            {
                "training_time": 0.12844749999931082,
                "prediction_time": 0.005904100002226187,
                "evaluation_time": 0.0008138000011967961,
                "mae": 27.88949946493878,
                "mape": 0.1331117915336962
            },
            {
                "training_time": 0.12959700000283192,
                "prediction_time": 0.006794700002501486,
                "evaluation_time": 0.001720000000204891,
                "mae": 27.177359391943476,
                "mape": 0.13318622479215197
            },
            {
                "training_time": 0.1319361999994726,
                "prediction_time": 0.006454700000176672,
                "evaluation_time": 0.0007618999989063013,
                "mae": 27.975362532853676,
                "mape": 0.1343679488173069
            }
        ]
    },
    "CatBoostRegressor": {
        "training_time": 0.6391056200001912,
        "prediction_time": 0.0040903600005549375,
        "evaluation_time": 0.0012381199994706549,
        "mae": 28.230205620145817,
        "mape": 0.135747424031838,
        "per_fold": [
            {
                "training_time": 0.7678024999986519,
                "prediction_time": 0.004891900000075111,
                "evaluation_time": 0.0015614000003552064,
                "mae": 28.13466321738662,
                "mape": 0.13672909745583092
            },
            {
                "training_time": 0.6099367999995593,
                "prediction_time": 0.0034720999974524602,
                "evaluation_time": 0.0015581999978167005,
                "mae": 28.85186638140564,
                "mape": 0.13677656453714082
            },
            {
                "training_time": 0.6257810999995854,
                "prediction_time": 0.005650900002365233,
                "evaluation_time": 0.0015717999995104037,
                "mae": 28.22276945016349,
                "mape": 0.1345574296299037
            },
            {
                "training_time": 0.6336842000018805,
                "prediction_time": 0.003789500002312707,
                "evaluation_time": 0.000749400001950562,
                "mae": 27.50415464362252,
                "mape": 0.1343054070127583
            },
            {
                "training_time": 0.5583235000012792,
                "prediction_time": 0.002647400000569178,
                "evaluation_time": 0.0007497999977204017,
                "mae": 28.437574408150827,
                "mape": 0.13636862152355636
            }
        ]
    }
}