{
    "LinearRegression": {
        "training_time": 0.00828989999863552,
        "prediction_time": 0.0013181399976019748,
        "evaluation_time": 0.0010125000000698492,
        "mae": 31.225940025282625,
        "mape": 0.16114540135210467,
        "per_fold": [
            {
                "training_time": 0.008747499996388797,
                "prediction_time": 0.0017541999986860901,
                "evaluation_time": 0.0010605999996187165,
                "mae": 31.182669174690243,
                "mape": 0.16309845285348132
            },
            {
                "training_time": 0.008130399997753557,
                "prediction_time": 0.001094599996577017,
                "evaluation_time": 0.0008113000003504567,
                "mae": 31.986300359535168,
                "mape": 0.16252408744237595
            },
            {
                "training_time": 0.00841249999939464,
                "prediction_time": 0.0011842999956570566,
                "evaluation_time": 0.0009682000018074177,
                "mae": 30.94796235036568,
                "mape": 0.15820283677184635
            },
            {
                "training_time": 0.007826299995940644,
                "prediction_time": 0.0010756999981822446,
                "evaluation_time": 0.0012339000022620894,
                "mae": 30.605736376661568,
                "mape": 0.1603145267038419
            },
            {
                "training_time": 0.008332800003699958,
                "prediction_time": 0.0014818999989074655,
                "evaluation_time": 0.0009884999963105656,
                "mae": 31.407031865160466,
                "mape": 0.16158710298897788
            }
        ]
    },
    "XGBRegressor": {
        "training_time": 0.6054505200023413,
        "prediction_time": 0.02684752000059234,
        "evaluation_time": 0.0008449600005405955,
        "mae": 27.56722640991211,
        "mape": 0.13374902904033661,
        "per_fold": [
            {
                "training_time": 0.681732800003374,
                "prediction_time": 0.006359899998642504,
                "evaluation_time": 0.0009296999996877275,
                "mae": 27.34015655517578,
                "mape": 0.13399486243724823
            },
            {
                "training_time": 0.5524911999964388,
                "prediction_time": 0.00677910000376869,
                "evaluation_time": 0.000785399999585934,
                "mae": 28.123714447021484,
                "mape": 0.13416935503482819
            },
            {
                "training_time": 0.5521808000048622,
                "prediction_time": 0.004885299997113179,
                "evaluation_time": 0.0007415000000037253,
                "mae": 27.643037796020508,
                "mape": 0.13294777274131775
            },
            {
                "training_time": 0.5981793000028119,
                "prediction_time": 0.10805439999967348,
                "evaluation_time": 0.0009546000001137145,
                "mae": 26.89424705505371,
                "mape": 0.1325237900018692
            },
            {
                "training_time": 0.6426685000042198,
                "prediction_time": 0.008158900003763847,
                "evaluation_time": 0.0008136000033118762,
                "mae": 27.834976196289062,
                "mape": 0.13510936498641968
            }
        ]
    },
    "LGBMRegressor": {
        "training_time": 0.44944070000055947,
        "prediction_time": 0.0075016800008597785,
        "evaluation_time": 0.0012288599988096393,
        "mae": 27.735761652434178,
        "mape": 0.1335581903332011,
        "per_fold": [
            {
                "training_time": 1.5652061000000685,
                "prediction_time": 0.007603899997775443,
                "evaluation_time": 0.0012714000040432438,
                "mae": 27.58733593742268,
                "mape": 0.13397226192262712
            },
            {
                "training_time": 0.17891450000024633,
                "prediction_time": 0.007436200001393445,
                "evaluation_time": 0.001595399997313507,
                "mae": 28.254408285080245,
                "mape": 0.13425347495711001
            },
            {
                "training_time": 0.16725420000148006,
                "prediction_time": 0.007853800001612399,
                "evaluation_time": 0.0011856999990413897,
                "mae": 27.7640377869463,
                "mape": 0.13229330150774007
            },
            {
                "training_time": 0.16726670000207378,
                "prediction_time": 0.007629100000485778,
                "evaluation_time": 0.0007232999996631406,
                "mae": 27.154965053058174,
                "mape": 0.13312460678633573
            },
            {
                "training_time": 0.1685619999989285,
                "prediction_time": 0.0069854000030318275,
                "evaluation_time": 0.0013684999939869158,
                "mae": 27.918061199663477,
                "mape": 0.1341473064921925
            }
        ]
    },
    "CatBoostRegressor": {
        "training_time": 0.6275587199997972,
        "prediction_time": 0.004472740001801867,
        "evaluation_time": 0.0014030599995749071,
        "mae": 28.229102604961916,
        "mape": 0.1357873667729343,
        "per_fold": [
            {
                "training_time": 0.7235074999989592,
                "prediction_time": 0.004206200006592553,
                "evaluation_time": 0.0015432000000146218,
                "mae": 28.074407805785253,
                "mape": 0.1361988854511957
            },
            {
                "training_time": 0.6237512000006973,
                "prediction_time": 0.005709099998057354,
                "evaluation_time": 0.0015971999964676797,
                "mae": 28.8750895794231,
                "mape": 0.13687906234477334
            },
            {
                "training_time": 0.5873360999976285,
                "prediction_time": 0.004354500000772532,
                "evaluation_time": 0.0011936000009882264,
                "mae": 28.19455462418083,
                "mape": 0.13453798696149472
            },
            {
                "training_time": 0.6167254000029061,
                "prediction_time": 0.003664300005766563,
                "evaluation_time": 0.0013432999985525385,
                "mae": 27.57588702173395,
                "mape": 0.13490090560684317
            },
            {
                "training_time": 0.5864733999987948,
                "prediction_time": 0.004429599997820333,
                "evaluation_time": 0.0013380000018514693,
                "mae": 28.42557399368645,
                "mape": 0.13641999350036454
            }
        ]
    }
}